pychronotab/__init__.py
pychronotab/_version.py
pychronotab/compat_croniter.py
pychronotab/core.py
pychronotab/exceptions.py
pychronotab/fields.py
pychronotab-1.0.0.dist-info/METADATA
pychronotab-1.0.0.dist-info/WHEEL
pychronotab-1.0.0.dist-info/licenses/LICENSE
pychronotab-1.0.0.dist-info/RECORD
