Metadata-Version: 2.4
Name: pychronotab
Version: 1.0.0
Summary: A cron expression iterator with croniter-compatible API, supporting 5 and 6-field cron (with seconds). Named after Chronos (time) to avoid conflicts with crontab packages.
Project-URL: Homepage, https://github.com/millsks/pychronotab
Project-URL: Issues, https://github.com/millsks/pychronotab/issues
Project-URL: Documentation, https://github.com/millsks/pychronotab
Author: millsks
License: MIT License
License-File: LICENSE
Keywords: cron,croniter,datetime,scheduler,scheduling,time
Classifier: Development Status :: 4 - Beta
Classifier: Intended Audience :: Developers
Classifier: License :: OSI Approved :: MIT License
Classifier: Operating System :: OS Independent
Classifier: Programming Language :: Python :: 3
Classifier: Programming Language :: Python :: 3.10
Classifier: Programming Language :: Python :: 3.11
Classifier: Programming Language :: Python :: 3.12
Classifier: Programming Language :: Python :: 3.13
Classifier: Topic :: Software Development :: Libraries
Classifier: Topic :: Software Development :: Libraries :: Python Modules
Requires-Python: >=3.10
